korNum/__init__.py
korNum/chgFormat.py
korNum/chgList.py
korNum-0.0.2.2.dist-info/LICENSE
korNum-0.0.2.2.dist-info/METADATA
korNum-0.0.2.2.dist-info/WHEEL
korNum-0.0.2.2.dist-info/top_level.txt
korNum-0.0.2.2.dist-info/RECORD
