Metadata-Version: 2.1
Name: korNum
Version: 0.0.2.2
Summary: change Korean tex number <---> Arabian number
Home-page: https://github.com/study-ai-data/korNum
Author: ('Kyeongnam Kim',)
Author-email: devokkn@gmail.com
License: MIT
Download-URL: https://github.com/study-ai-data/korNum
Platform: UNKNOWN
Classifier: Programming Language :: Python :: 3.6
Classifier: Programming Language :: Python :: 3.7
Classifier: Programming Language :: Python :: 3.8
Classifier: Programming Language :: Python :: 3.9
Classifier: License :: OSI Approved :: MIT License
Classifier: Natural Language :: Korean
Classifier: Operating System :: Microsoft :: Windows
Classifier: Operating System :: MacOS
Classifier: Operating System :: POSIX
